udao/__init__.py
udao/data/__init__.py
udao/data/containers/__init__.py
udao/data/containers/base_container.py
udao/data/containers/query_structure_container.py
udao/data/containers/tabular_container.py
udao/data/extractors/__init__.py
udao/data/extractors/base_extractors.py
udao/data/extractors/predicate_embedding_extractor.py
udao/data/extractors/query_structure_extractor.py
udao/data/extractors/tabular_extractor.py
udao/data/handler/data_handler.py
udao/data/handler/data_processor.py
udao/data/iterators/__init__.py
udao/data/iterators/base_iterator.py
udao/data/iterators/query_plan_iterator.py
udao/data/iterators/tabular_iterator.py
udao/data/predicate_embedders/__init__.py
udao/data/predicate_embedders/base_predicate_embedder.py
udao/data/predicate_embedders/doc2vec_embedder.py
udao/data/predicate_embedders/utils.py
udao/data/predicate_embedders/word2vec_embedder.py
udao/data/preprocessors/__init__.py
udao/data/preprocessors/base_preprocessor.py
udao/data/preprocessors/normalize_preprocessor.py
udao/data/preprocessors/one_hot_preprocessor.py
udao/data/tests/__init__.py
udao/data/tests/conftest.py
udao/data/tests/embedders/__init__.py
udao/data/tests/embedders/test_doc2vec_embedder.py
udao/data/tests/embedders/test_utils.py
udao/data/tests/embedders/test_word2vec_embedder.py
udao/data/tests/extractors/__init__.py
udao/data/tests/extractors/test_query_embedding_extractor.py
udao/data/tests/extractors/test_query_structure_extractor.py
udao/data/tests/extractors/test_tabular_extractor.py
udao/data/tests/handler/__init__.py
udao/data/tests/handler/test_data_processor.py
udao/data/tests/handler/test_handler.py
udao/data/tests/iterators/__init__.py
udao/data/tests/iterators/dummy_udao_iterator.py
udao/data/tests/iterators/test_query_graph_iterator.py
udao/data/tests/iterators/test_tabular_iterator.py
udao/data/tests/preprocessors/__init__.py
udao/data/tests/preprocessors/test_normalize_preprocessor.py
udao/data/tests/preprocessors/test_one_hot_preprocessor.py
udao-1.0.5.dist-info/LICENSE
udao-1.0.5.dist-info/METADATA
udao-1.0.5.dist-info/WHEEL
udao-1.0.5.dist-info/top_level.txt
udao-1.0.5.dist-info/RECORD
