Metadata-Version: 2.2
Name: udao
Version: 1.0.5
Author-email: Chenghao Lyu <chenghao@cs.umass.edu>, Julien Fontanarava <julien.fontanarava@gmail.com>
Maintainer-email: Chenghao Lyu <chenghao@cs.umass.edu>
License:                                  Apache License
Project-URL: Bug Reports, https://github.com/angryrou/udao/issues
Project-URL: Source, https://github.com/angryrou/udao/
Classifier: Development Status :: 3 - Alpha
Classifier: Intended Audience :: Developers
Classifier: Topic :: Software Development :: Build Tools
Classifier: License :: OSI Approved :: Apache Software License
Classifier: Programming Language :: Python :: 3
Classifier: Programming Language :: Python :: 3.9
Classifier: Programming Language :: Python :: 3.10
Classifier: Programming Language :: Python :: 3.11
Classifier: Programming Language :: Python :: 3 :: Only
Requires-Python: >=3.9
License-File: LICENSE
Requires-Dist: mypy==1.5.1
Requires-Dist: mypy-extensions==1.0.0
Requires-Dist: networkx>=2.8.8
Requires-Dist: networkx-stubs==0.0.1
Requires-Dist: numpy<2.0.0,>=1.24
Requires-Dist: pandas>=2.0.2
Requires-Dist: pandas-stubs==2.0.2.230605
Requires-Dist: scikit-learn>=1.3.1
Requires-Dist: scipy<1.13.0,>=1.7.0
Requires-Dist: pytorch-warmup==0.1.1
Requires-Dist: lightning<=2.1.0,>=2.0.9
Requires-Dist: torchmetrics>=1.1.2
Requires-Dist: gensim==4.3.2
Requires-Dist: matplotlib<3.9.0,>=3.8.1
Requires-Dist: Platypus-Opt==1.1.0
Requires-Dist: tensorboard==2.15.1
Requires-Dist: dgl<=1.1.3,>=1.1.2
Requires-Dist: torch==2.0.1
Provides-Extra: dev
Requires-Dist: pre-commit==3.4.0; extra == "dev"
Requires-Dist: types-requests==2.28.0; extra == "dev"
Requires-Dist: requests>=2.28; extra == "dev"
Requires-Dist: pytest==7.4.2; extra == "dev"
Requires-Dist: pytest-cov==4.1.0; extra == "dev"
Requires-Dist: pytest-mock==3.12.0; extra == "dev"
Requires-Dist: chardet==5.2.0; extra == "dev"
Requires-Dist: sphinx==7.2.6; extra == "dev"
Requires-Dist: sphinx-book-theme==1.1.0; extra == "dev"
